{
  "parent": "minecraft:recipes/root",
  "rewards": {
    "recipes": [
      "minecraft:tofuladder_ishi_from_tofuishi_brick_stonecutting"
    ]
  },
  "criteria": {
    "has_tofuishi_brick": {
      "trigger": "minecraft:inventory_changed",
      "conditions": {
        "items": [
          {
            "items": [
              "tofucraft:tofuishi_brick"
            ]
          }
        ]
      }
    },
    "has_the_recipe": {
      "trigger": "minecraft:recipe_unlocked",
      "conditions": {
        "recipe": "minecraft:tofuladder_ishi_from_tofuishi_brick_stonecutting"
      }
    }
  },
  "requirements": [
    [
      "has_tofuishi_brick",
      "has_the_recipe"
    ]
  ]
}