{
  "type" : "minecraft:chest",
  "pools" : [
    {
      "rolls" : {
        "min" : 6.0,
        "max" : 8.0,
        "type" : "minecraft:uniform"
      },
      "entries" : [
        {
          "type" : "minecraft:item",
          "weight" : 10,
          "name" : "tofucraft:tofumetal",
          "functions" : [
            {
              "function" : "minecraft:set_count",
              "count" : {
                "min" : 1.0,
                "max" : 2.0,
                "type" : "minecraft:uniform"
              }
            }
          ]
        },
        {
          "type" : "minecraft:item",
          "weight" : 5,
          "name" : "tofucraft:zundaruby",
          "functions" : [
            {
              "function" : "minecraft:set_count",
              "count" : {
                "min" : 1.0,
                "max" : 2.0,
                "type" : "minecraft:uniform"
              }
            }
          ]
        }
      ]
    },
    {
      "rolls" : 1,
      "entries" : [
        {
          "type" : "minecraft:item",
          "weight" : 10,
          "name" : "tofucraft:bucket_soymilk"
        }
      ]
    }
  ]
}